{
    "language":"Ukrainian",
    "main-page":
    {        
        "title":"Лабораторна робота 1",
        "langs":[
            "English", "Ukrainian"
        ],
        "description":"Це наше сховище соків. Ви можете використовувати його для зберігання своїх соків. Використовуйте кнопкиЖ Додати, Редагувати, Видалити для маніпулювання данними",
        "lv-title":"Список соків:",
        "buttons":
        {
            "add-btn":"Додати",
            "edit-btn":"Редагувати",
            "del-btn":"Видалити"
        }
    },
    "add-offcanv":
    {

    },
    "edit-offcanv":
    {

    }    
}